karafuru/__init__.py
karafuru/__main__.py
karafuru/py.typed
karafuru-0.1.1.dist-info/entry_points.txt
karafuru-0.1.1.dist-info/LICENSE
karafuru-0.1.1.dist-info/WHEEL
karafuru-0.1.1.dist-info/METADATA
karafuru-0.1.1.dist-info/RECORD
